{
    "users": [
        {
            "id": 0,
            "uName": "Johny123",
            "pwd": "12345",
            "firstName": "John",
            "lastName": "Caper",
            "email": "johny123@email.com",
            "phone": "+353232565898",
            "country": "Ireland",
            "address": "something, something, Sligo",
            "eircode": "F91 8562"
        },
        {
            "id": 1,
            "uName": "Johny256",
            "pwd": "jakdka",
            "firstName": "John",
            "lastName": "Caper",
            "email": "johny1234@email.com",
            "phone": "+353234562562",
            "country": "Ireland",
            "address": "something, something, Sligo",
            "eircode": "F91 8562"
        }
    ]
}
